qloud/QloudAuthentication.py
qloud/__init__.py
qloud_wsgi-0.2.0.dist-info/WHEEL
qloud_wsgi-0.2.0.dist-info/METADATA
qloud_wsgi-0.2.0.dist-info/license_files/LICENSE
qloud_wsgi-0.2.0.dist-info/RECORD
