Metadata-Version: 2.1
Name: qloud-wsgi
Version: 0.2.0
Summary: Qloud Integration for WSGI applications
License: MIT
Author-email: Qloud Development Team <dev@qloud.network>
Requires-Python: >=3.7
Classifier: Environment :: Web Environment
Classifier: Intended Audience :: Developers
Classifier: License :: OSI Approved :: MIT License
Classifier: Operating System :: OS Independent
Classifier: Programming Language :: Python :: 3
Classifier: Topic :: Internet :: WWW/HTTP :: WSGI :: Middleware
Classifier: Topic :: Security
Requires-Dist: PyJWT>=1.7.1
Requires-Dist: werkzeug>=0.14.1
Project-URL: Bug Tracker, https://github.com/QloudNetwork/qloud-integrations/issues
Project-URL: Homepage, https://github.com/QloudNetwork/qloud-integrations
